pyrope.cpython-313-darwin.so
py_librope-0.0.2.dist-info/LICENSE
py_librope-0.0.2.dist-info/METADATA
py_librope-0.0.2.dist-info/WHEEL
py_librope-0.0.2.dist-info/top_level.txt
py_librope-0.0.2.dist-info/RECORD
