Metadata-Version: 2.2
Name: py-librope
Version: 0.0.2
Summary: Python bindings for librope (https://www.github.com/josephg/librope)
Home-page: https://github.com/takeiteasy/pyrope
Author: George Watson
Author-email: George Watson <gigolo@hotmail.co.uk>
Project-URL: Homepage, https://github.com/takeiteasy/pyrope
Project-URL: Issues, https://github.com/takeiteasy/pyrope/issues
Classifier: Programming Language :: Python :: 3
Classifier: License :: OSI Approved :: MIT License
Classifier: Operating System :: OS Independent
Requires-Python: >=3.8
License-File: LICENSE
Dynamic: author
Dynamic: home-page
